README.md
setup.cfg
setup.py
pywrk.egg-info/PKG-INFO
pywrk.egg-info/SOURCES.txt
pywrk.egg-info/dependency_links.txt
pywrk.egg-info/entry_points.txt
pywrk.egg-info/requires.txt
pywrk.egg-info/top_level.txt
wrk/__init__.py
wrk/main.py