Metadata-Version: 2.1
Name: pywrk
Version: 0.2.0
Summary: Small http benchmarking tool written in python
Home-page: https://github.com/superjcd/pywrk
Author: Jiang Chaodi
Author-email: 929760274@qq.com
License: BSD
Download-URL: https://github.com/superjcd/py-wrk/tarball/0.2.0
Platform: UNKNOWN
Classifier: Development Status :: 3 - Alpha
Classifier: Intended Audience :: Developers
Classifier: Programming Language :: Python :: 3
